{
  "scenario_text": [
    {
      "key": "EP09_S9000_0001",
      "value": "*sigh*"
    },
    {
      "key": "EP09_S9000_0002",
      "value": "You’re still awake?"
    },
    {
      "key": "EP09_S9000_0003",
      "value": "Ryo, Kunemon..."
    },
    {
      "key": "EP09_S9000_0004",
      "value": "Kew..."
    },
    {
      "key": "EP09_S9000_0005",
      "value": "Can’t sleep, huh?"
    },
    {
      "key": "EP09_S9000_0006",
      "value": "Yes, we made it back somehow, but...after\na battle like that, I can’t calm my nerves."
    },
    {
      "key": "EP09_S9000_0007",
      "value": "Shuuji..."
    },
    {
      "key": "EP09_S9000_0008",
      "value": "Can’t blame ya, man. I’d be fronting if\nI said I felt much different."
    },
    {
      "key": "EP09_S9000_0009",
      "value": "I’ve been thinking about how to escape this\nworld—other than asking the enemy, I mean."
    },
    {
      "key": "EP09_S9000_0010",
      "value": "It seems everyone’s done the same, but...\nI want to help the professor look for a clue."
    },
    {
      "key": "EP09_S9000_0011",
      "value": "Help the professor? Heh, ain’t you supposed\nto be taking point on this, Fearless Leader?"
    },
    {
      "key": "EP09_S9000_0012",
      "value": "Ahaha... Come on, be nice..."
    },
    {
      "key": "EP09_S9000_0013",
      "value": "Aoi’s doing her best to lead everyone. She’s\nlike a mother to all of us."
    },
    {
      "key": "EP09_S9000_0014",
      "value": "A mother... Yeah, I feel you."
    },
    {
      "key": "EP09_S9000_0015",
      "value": "Of course I want to be the leader, but that’d\njust be me chasing my father’s shadow."
    },
    {
      "key": "EP09_S9000_0016",
      "value": "Now, I think a leader is something different\nfrom the forceful leadership style he uses."
    },
    {
      "key": "EP09_S9000_0017",
      "value": "Seeing the professor, I’ve come to think that\na leader should be generous and intellectual."
    },
    {
      "key": "EP09_S9000_0018",
      "value": "That’s why I want to stay close to him—to\nstudy his example with my own eyes."
    },
    {
      "key": "EP09_S9000_0019",
      "value": "Ah, I got you..."
    },
    {
      "key": "EP09_S9000_0020",
      "value": "Well, if we’re talking leaders... I’d say\nTakuma fits the bill more than anyone."
    },
    {
      "key": "EP09_S9000_0021",
      "value": "I know what you mean. He’s been a strong\ninfluence on my ideal of a leader."
    },
    {
      "key": "EP09_S9000_0022",
      "value": "We’ll have to just do our best until he comes\nback..."
    },
    {
      "key": "EP09_S9000_0023",
      "value": "Yeah, um...I mean, how do I say this..."
    },
    {
      "key": "EP09_S9000_0024",
      "value": "When he’s not around, I can’t just leave it\nall to you and Aoi..."
    },
    {
      "key": "EP09_S9000_0025",
      "value": "I’ll, uh... I’ll follow your lead, a’ight?"
    },
    {
      "key": "EP09_S9000_0026",
      "value": "Ryo..."
    },
    {
      "key": "EP09_S9000_0027",
      "value": "Sure, I’m glad I can rely on you."
    },
    {
      "key": "EP09_S9000_0028",
      "value": "I’ll d-do what I can too!"
    },
    {
      "key": "EP09_S9000_0029",
      "value": "Kewkew!"
    },
    {
      "key": "EP09_S9000_0030",
      "value": "Haha! Right, we’ll do this together!"
    }
  ]
}