{
  "scenario_text": [
    {
      "key": "EP02_S0011_0005",
      "value": "Takuma?"
    },
    {
      "key": "EP02_S0011_0006",
      "value": "Whoa!!!"
    },
    {
      "key": "EP02_S0011_0007",
      "value": "Oh, it’s just Agumon...\nDon’t sneak up on me like that!"
    },
    {
      "key": "EP02_S0011_0008",
      "value": "I saw you get up and followed you!"
    },
    {
      "key": "EP02_S0011_0009",
      "value": "What were you up to?"
    },
    {
      "key": "EP02_S0011_0010",
      "value": "Nothing special. It’s just that yesterday was\npretty intense."
    },
    {
      "key": "EP02_S0011_0011",
      "value": "We just wanted to go camping and this rock\ncreature attacked us."
    },
    {
      "key": "EP02_S0011_0012",
      "value": "Gotsumon!"
    },
    {
      "key": "EP02_S0011_0013",
      "value": "Yeah, Gotsumon attacked. We got away, \nbut this school was a spider creature’s lair!"
    },
    {
      "key": "EP02_S0011_0014",
      "value": "Dokugumon!"
    },
    {
      "key": "EP02_S0011_0015",
      "value": "It was all so confusing!\nI couldn’t keep up with it all."
    },
    {
      "key": "EP02_S0011_0016",
      "value": "Really? I thought you did great!"
    },
    {
      "key": "EP02_S0011_0017",
      "value": "It was touch and go. Even when a friend was\ncaptured, I could only help after Haru’s tip."
    },
    {
      "key": "EP02_S0011_0018",
      "value": "Heheheh. Everyone was so scared when he\npopped up! Even though he’s no ghost."
    },
    {
      "key": "EP02_S0011_0019",
      "value": "You can’t blame them. When I first met\nhim and his sister, I was surprised, too."
    },
    {
      "key": "EP02_S0011_0020",
      "value": "We were exhausted yesterday, but there’s\na lot to think about."
    },
    {
      "key": "EP02_S0011_0021",
      "value": "Think about? Like what?"
    },
    {
      "key": "EP02_S0011_Q1",
      "value": "(Right now, we should think about...)"
    },
    {
      "key": "EP02_S0011_Q1_A1",
      "value": "Keeping everyone safe."
    },
    {
      "key": "EP02_S0011_Q1_A2",
      "value": "The next fight!"
    },
    {
      "key": "EP02_S0011_Q1_A3",
      "value": "What’s happening here."
    },
    {
      "key": "EP02_S0011_0022",
      "value": "Let’s start with how to protect ourselves.\nOthers like Dokugumon could attack again."
    },
    {
      "key": "EP02_S0011_0023",
      "value": "Yeah. There are other dangerous ones\nout there."
    },
    {
      "key": "EP02_S0011_0024",
      "value": "We need a base where we can rest in safety.\nIt’d be great if we could use this school..."
    },
    {
      "key": "EP02_S0011_0025",
      "value": "If Dokugumon is not the only one, we need to\nfigure out some protection."
    },
    {
      "key": "EP02_S0011_0026",
      "value": "Leave the fighting to me!"
    },
    {
      "key": "EP02_S0011_0027",
      "value": "Thanks, Agumon! I’ll also think about how to\nmake myself stronger."
    },
    {
      "key": "EP02_S0011_0028",
      "value": "Unless we figure out what’s happening to us,\nI think we can’t expect to get out of here."
    },
    {
      "key": "EP02_S0011_0029",
      "value": "Right, but how exactly can we find out?"
    },
    {
      "key": "EP02_S0011_0030",
      "value": "Exactly. I can’t think of anything myself,\nbut if we all put our heads together..."
    },
    {
      "key": "EP02_S0011_0031",
      "value": "Besides, while we wait to be rescued, we\nneed to figure out food, bath and sleep..."
    },
    {
      "key": "EP02_S0011_0032",
      "value": "Hmm..."
    },
    {
      "key": "EP02_S0011_0033",
      "value": "Takuma? You okay?"
    },
    {
      "key": "EP02_S0011_0034",
      "value": "*sigh* I’m not coming up with anything.\nLet’s ask everyone."
    },
    {
      "key": "EP02_S0011_0035",
      "value": "You got it! Let’s do that!"
    }
  ]
}