{
  "scenario_text": [
    {
      "key": "EP13_S9472_0001",
      "value": ""
    },
    {
      "key": "EP13_S9472_0002",
      "value": ""
    },
    {
      "key": "EP13_S9472_0003",
      "value": ""
    },
    {
      "key": "EP13_S9472_0004",
      "value": ""
    },
    {
      "key": "EP13_S9472_0005",
      "value": ""
    },
    {
      "key": "EP13_S9472_0006",
      "value": ""
    },
    {
      "key": "EP13_S9472_0007",
      "value": ""
    },
    {
      "key": "EP13_S9472_0008",
      "value": ""
    },
    {
      "key": "EP13_S9472_0009",
      "value": ""
    }
  ]
}