{
  "scenario_text": [
    {
      "key": "EP07_S3118_0001",
      "value": "Stand aside and let us pass!\nWe have no reason to fight you!"
    },
    {
      "key": "EP07_S3118_0002",
      "value": "I have no intention of stepping aside before\ncrushing your delusions."
    },
    {
      "key": "EP07_S3118_0010",
      "value": "I have no intention of stepping aside before\ncrushing your delusions."
    },
    {
      "key": "EP07_S3118_0003",
      "value": "They aren’t delusions.\nLabramon protects me."
    },
    {
      "key": "EP07_S3118_0004",
      "value": "My heart calls out to protect her.\nThe same should be true for you."
    },
    {
      "key": "EP07_S3118_0005",
      "value": "They are not delusions.\nLabramon and I are bound to each other."
    },
    {
      "key": "EP07_S3118_0006",
      "value": "I naturally want to protect her.\nMy bond with her makes it so!"
    },
    {
      "key": "EP07_S3118_0007",
      "value": "They are not delusions.\nI believe I am bound to Labramon!"
    },
    {
      "key": "EP07_S3118_0008",
      "value": "You might not see it, but there truly is\na bond between us."
    },
    {
      "key": "EP07_S3118_0009",
      "value": "...And you still don’t understand why I say\nit’s a delusion?"
    },
    {
      "key": "EP07_S3118_0011",
      "value": "Stand aside and let us pass! We have no\nreason to fight you!"
    },
    {
      "key": "EP07_S3118_0012",
      "value": "I have no intention of stepping aside before\ncrushing your delusions."
    },
    {
      "key": "EP07_S3118_0013",
      "value": "Our faith is no delusion. Dobermon protects\nme."
    },
    {
      "key": "EP07_S3118_0014",
      "value": "Of course I’d want to protect her. You should\nunderstand how I feel!"
    },
    {
      "key": "EP07_S3118_0015",
      "value": "Our faith is no delusion. Dobermon and me are\nbound to each other."
    },
    {
      "key": "EP07_S3118_0016",
      "value": "Our bond can’t be seen by the naked eye, but\nit’s there. Reason enough for me to fight!"
    },
    {
      "key": "EP07_S3118_0017",
      "value": "Our faith is no delusion. My heart is bound\nto Dobermon, I know it!"
    },
    {
      "key": "EP07_S3118_0018",
      "value": "You might not see it, but there truly is\na bond between us."
    },
    {
      "key": "EP07_S3118_0019",
      "value": "...And you still don’t understand why I say\nit’s a delusion?"
    },
    {
      "key": "EP07_S3118_0020",
      "value": "Stand aside and let us pass! We have no\nreason to fight you!"
    },
    {
      "key": "EP07_S3118_0021",
      "value": "I have no intention of stepping aside before\ncrushing your delusions."
    },
    {
      "key": "EP07_S3118_0022",
      "value": "Our faith is no delusion. Cerberusmon\nprotects me."
    },
    {
      "key": "EP07_S3118_0023",
      "value": "I’d expect you understand a heart that cries\nout to protect."
    },
    {
      "key": "EP07_S3118_0024",
      "value": "Our faith is no delusion. Cerberusmon and\nme are bound to each other."
    },
    {
      "key": "EP07_S3118_0025",
      "value": "A voice inside me compels me to protect. That\nidea shouldn’t be foreign to you, Garurumon."
    },
    {
      "key": "EP07_S3118_0026",
      "value": "Our faith is no delusion. My heart is bound\nto Cerberusmon, I know it!"
    },
    {
      "key": "EP07_S3118_0027",
      "value": "Our bond can’t be seen by the naked eye, but\nit’s there. I’d give my life for that bond."
    },
    {
      "key": "EP07_S3118_0028",
      "value": "...And you still don’t understand why I say\nit’s a delusion?"
    }
  ]
}