{
  "scenario_text": [
    {
      "key": "EP12_S1000_0001",
      "value": "Come in, HQ. This is Alpha Squad. No targets\nfound."
    },
    {
      "key": "EP12_S1000_0002",
      "value": "Copy that, Alpha Squad. Continue the search."
    },
    {
      "key": "EP12_S1000_0003",
      "value": "I’m sorry, but could you go over things again\nfor us? Any idea where they might be?"
    },
    {
      "key": "EP12_S1000_0004",
      "value": "Well, no, I’m afraid not, really. They’re not\nthe type to just go off on their own..."
    },
    {
      "key": "EP12_S1000_0005",
      "value": "Hey, did you hear? A college professor and\nsome local kids are missing too."
    },
    {
      "key": "EP12_S1000_0006",
      "value": "Yeah, and the professor’s in his sixties.\nEven the adults are getting lost! It’s crazy."
    },
    {
      "key": "EP12_S1000_0007",
      "value": "Think it’s a mass disappearance? I heard one\nhappened here fifty years ago."
    },
    {
      "key": "EP12_S1000_0008",
      "value": "Between you and me, I heard they all got\nspirited away. Like, by an actual monster."
    },
    {
      "key": "EP12_S1000_0009",
      "value": "Yeah, something weird is on the loose out\nhere in the mountains. I saw it."
    },
    {
      "key": "EP12_S1000_0010",
      "value": "At first I thought maybe I was just imagining\nthings, but check this out."
    },
    {
      "key": "EP12_S1000_0011",
      "value": "Man, that’s really blurry."
    },
    {
      "key": "EP12_S1000_0012",
      "value": "I kind of panicked, okay? But what do you\nthink it is?"
    },
    {
      "key": "EP12_S1000_0013",
      "value": "Whoa... It’s like some kind of monster! That\nis definitely not just an animal."
    },
    {
      "key": "EP12_S1000_0014",
      "value": "This one looks like it could be a clown? Then\nagain, it doesn’t seem human..."
    },
    {
      "key": "EP12_S1000_0015",
      "value": "Look, these two are facing off against each\nother! It’s like they’re about to fight!"
    },
    {
      "key": "EP12_S1000_0016",
      "value": "Maybe these are the monsters that have been\nkidnapping people!"
    },
    {
      "key": "EP12_S1000_0017",
      "value": "This is wild! I bet it would really blow up\nif you put it online!"
    },
    {
      "key": "EP12_S1000_0018",
      "value": "No way. Everyone would just think it was\na fake."
    },
    {
      "key": "EP12_S1000_0019",
      "value": "Then again... I guess it couldn’t hurt to see\nwhat happens."
    }
  ]
}