{
  "scenario_text": [
    {
      "key": "EP08_S0148_0005",
      "value": "That was unreal! So freakin’ cool! It’s like\nsomething straight out of a movie!"
    },
    {
      "key": "EP08_S0148_0006",
      "value": "(Ugh, this is the last thing I need right\nnow!)"
    },
    {
      "key": "EP08_S0148_0007",
      "value": "Hey, let’s get closer so we can take a video!"
    },
    {
      "key": "EP08_S0148_0008",
      "value": "Sweet! This is gonna blow up on social media\nfor sure!"
    },
    {
      "key": "EP08_S0148_0009",
      "value": "Take this!"
    },
    {
      "key": "EP08_S0148_0010",
      "value": "Whoa! That was a close one! I almost got hit!"
    },
    {
      "key": "EP08_S0148_0011",
      "value": "Yikes! Watch out for that debris!"
    },
    {
      "key": "EP08_S0148_0012",
      "value": "Everyone stay back! This is really dangerous,\nso you need to keep your distance!"
    }
  ]
}