{
  "scenario_text": [
    {
      "key": "EP12_S7103_0001",
      "value": "Professor, last time we came here you said\nyou hadn’t finished investigating, but..."
    },
    {
      "key": "EP12_S7103_0002",
      "value": "...have you found out anything else?"
    },
    {
      "key": "EP12_S7103_0003",
      "value": "No, I’m afraid I wasn’t able to make any new\ndiscoveries concerning these murals."
    },
    {
      "key": "EP12_S7103_0004",
      "value": "As I said before, it seems some immense power\nbrought tragedy to a great many."
    },
    {
      "key": "EP12_S7103_0005",
      "value": "Though I can’t get any more than that from\nthis mural."
    },
    {
      "key": "EP12_S7103_0006",
      "value": "What about this one?"
    },
    {
      "key": "EP12_S7103_0007",
      "value": "Wasn’t it...humans and Kemonogami suffering?\nNo, something about four god-like beings..."
    },
    {
      "key": "EP12_S7103_0008",
      "value": "Yes, the four god-like beings from ancient\nlegends. This mural includes aspects of them."
    },
    {
      "key": "EP12_S7103_0009",
      "value": "And the composition still bothers me. Heaven\nis traditionally above and hell below."
    },
    {
      "key": "EP12_S7103_0010",
      "value": "No, I’m afraid I can’t offer any\ninterpretation of this mural."
    },
    {
      "key": "EP12_S7103_0011",
      "value": "Humans suffering, four god-like beings..."
    },
    {
      "key": "EP12_S7103_0012",
      "value": "Hmm... If only I knew how this connected to\nthe other murals, I might understand it."
    }
  ]
}