{
  "scenario_text": [
    {
      "key": "EP03_S2444_0001",
      "value": "Incidentally, what are all of you doing here?"
    },
    {
      "key": "EP03_S2444_0002",
      "value": "We’re trying to get to that radio tower over\nthere."
    },
    {
      "key": "EP03_S2444_0003",
      "value": "Radio tower?"
    },
    {
      "key": "EP03_S2444_0004",
      "value": "You know how there’s no signal? We’re hoping\nif we get there our cell phones will work."
    },
    {
      "key": "EP03_S2444_0005",
      "value": "Your...cell phones?"
    },
    {
      "key": "EP03_S2444_0006",
      "value": "Right. Then we’ll be able to call for help.\nWe could even get you home, too."
    },
    {
      "key": "EP03_S2444_0007",
      "value": "Oh... Yes, that would be wonderful."
    },
    {
      "key": "EP03_S2444_0008",
      "value": "Well, if you’re heading for the radio tower,\nI know a way to get there."
    },
    {
      "key": "EP03_S2444_0009",
      "value": "Seriously?!"
    },
    {
      "key": "EP03_S2444_0010",
      "value": "If that’s true, it would be a big help!"
    },
    {
      "key": "EP03_S2444_0011",
      "value": "Oh, yes. Just up ahead there’s a vehicle that\ngoes to the summit. What was it called again?"
    },
    {
      "key": "EP03_S2444_0012",
      "value": "Ah, I remember, it’s a...cable car."
    },
    {
      "key": "EP03_S2444_0013",
      "value": "I could take you there if you’d like."
    },
    {
      "key": "EP03_S2444_0014",
      "value": "Wow, who would’ve thought there’d be a cable\ncar? This is great! It’ll make things easy."
    },
    {
      "key": "EP03_S2444_0015",
      "value": "It sure will! Thanks for telling us!"
    },
    {
      "key": "EP03_S2444_0016",
      "value": "(Wait a minute, something about this isn’t\nadding up...)"
    },
    {
      "key": "EP03_S2444_0017",
      "value": "Why come here then?"
    },
    {
      "key": "EP03_S2444_0018",
      "value": "What do you mean?"
    },
    {
      "key": "EP03_S2444_0019",
      "value": "I mean, if you know the way to the tower, why\ncome out here where there’s no signal?"
    },
    {
      "key": "EP03_S2444_0020",
      "value": "Oh, yeah, that’s a good question."
    },
    {
      "key": "EP03_S2444_0021",
      "value": "Honestly, it seemed like you didn’t know what\nthe tower was at first, or even cell phones."
    },
    {
      "key": "EP03_S2444_0022",
      "value": "What? So you are a monster?!"
    },
    {
      "key": "EP03_S2444_0023",
      "value": "No! I just don’t own a cell phone, so there\nwas no reason for me to stay by the tower."
    },
    {
      "key": "EP03_S2444_0100",
      "value": "Heaven forbid! I just thought someone could\nbe nearby, so I came looking for them."
    },
    {
      "key": "EP03_S2444_0101",
      "value": "I’ve wandered all over looking for help,\nusing that radio tower as a landmark."
    },
    {
      "key": "EP03_S2444_0024",
      "value": "I’m sorry if my manner misled you. I can be\na bit clueless sometimes."
    },
    {
      "key": "EP03_S2444_0025",
      "value": "Oh... Okay, then. Sorry about the\nmisunderstanding."
    },
    {
      "key": "EP03_S2444_0026",
      "value": "(Was it a misunderstanding? Her explanation\njust now seemed pretty fishy.)"
    },
    {
      "key": "EP03_S2444_0027",
      "value": "If you’re trying to get to the tower, I can\nshow you the way. Heheh."
    }
  ]
}